{"dependencies":[{"name":"/Users/aleksi.skantz/Tavaraa/purescript/letsdopurescript/package.json","includedInParent":true,"mtime":1530452000261}],"generated":{"js":"// Generated by purs version 0.12.0\n\"use strict\";\n\nvar TypeEquals = function TypeEquals(from, to) {\n    this.from = from;\n    this.to = to;\n};\nvar to = function to(dict) {\n    return dict.to;\n};\nvar refl = new TypeEquals(function (a) {\n    return a;\n}, function (a) {\n    return a;\n});\nvar from = function from(dict) {\n    return dict.from;\n};\nmodule.exports = {\n    TypeEquals: TypeEquals,\n    to: to,\n    from: from,\n    refl: refl\n};","map":{"mappings":[{"generated":{"line":1,"column":0},"source":"output/Type.Equality/index.js","original":{"line":1,"column":0}},{"generated":{"line":2,"column":0},"source":"output/Type.Equality/index.js","original":{"line":2,"column":0}},{"generated":{"line":4,"column":0},"source":"output/Type.Equality/index.js","original":{"line":3,"column":0}},{"name":"TypeEquals","generated":{"line":4,"column":4},"source":"output/Type.Equality/index.js","original":{"line":3,"column":4}},{"generated":{"line":4,"column":17},"source":"output/Type.Equality/index.js","original":{"line":3,"column":17}},{"name":"TypeEquals","generated":{"line":4,"column":26},"source":"output/Type.Equality/index.js","original":{"line":3,"column":4}},{"generated":{"line":4,"column":36},"source":"output/Type.Equality/index.js","original":{"line":3,"column":17}},{"name":"from","generated":{"line":4,"column":37},"source":"output/Type.Equality/index.js","original":{"line":3,"column":27}},{"generated":{"line":4,"column":41},"source":"output/Type.Equality/index.js","original":{"line":3,"column":17}},{"name":"to","generated":{"line":4,"column":43},"source":"output/Type.Equality/index.js","original":{"line":3,"column":33}},{"generated":{"line":4,"column":45},"source":"output/Type.Equality/index.js","original":{"line":3,"column":17}},{"generated":{"line":4,"column":47},"source":"output/Type.Equality/index.js","original":{"line":3,"column":37}},{"generated":{"line":5,"column":0},"source":"output/Type.Equality/index.js","original":{"line":4,"column":4}},{"name":"from","generated":{"line":5,"column":9},"source":"output/Type.Equality/index.js","original":{"line":4,"column":9}},{"generated":{"line":5,"column":13},"source":"output/Type.Equality/index.js","original":{"line":4,"column":4}},{"name":"from","generated":{"line":5,"column":16},"source":"output/Type.Equality/index.js","original":{"line":4,"column":16}},{"generated":{"line":5,"column":20},"source":"output/Type.Equality/index.js","original":{"line":4,"column":4}},{"generated":{"line":6,"column":0},"source":"output/Type.Equality/index.js","original":{"line":5,"column":4}},{"name":"to","generated":{"line":6,"column":9},"source":"output/Type.Equality/index.js","original":{"line":5,"column":9}},{"generated":{"line":6,"column":11},"source":"output/Type.Equality/index.js","original":{"line":5,"column":4}},{"name":"to","generated":{"line":6,"column":14},"source":"output/Type.Equality/index.js","original":{"line":5,"column":14}},{"generated":{"line":6,"column":16},"source":"output/Type.Equality/index.js","original":{"line":5,"column":4}},{"generated":{"line":7,"column":0},"source":"output/Type.Equality/index.js","original":{"line":6,"column":1}},{"generated":{"line":7,"column":1},"source":"output/Type.Equality/index.js","original":{"line":3,"column":0}},{"generated":{"line":8,"column":0},"source":"output/Type.Equality/index.js","original":{"line":7,"column":0}},{"name":"to","generated":{"line":8,"column":4},"source":"output/Type.Equality/index.js","original":{"line":7,"column":4}},{"generated":{"line":8,"column":9},"source":"output/Type.Equality/index.js","original":{"line":7,"column":9}},{"name":"to","generated":{"line":8,"column":18},"source":"output/Type.Equality/index.js","original":{"line":7,"column":4}},{"generated":{"line":8,"column":20},"source":"output/Type.Equality/index.js","original":{"line":7,"column":9}},{"name":"dict","generated":{"line":8,"column":21},"source":"output/Type.Equality/index.js","original":{"line":7,"column":19}},{"generated":{"line":8,"column":25},"source":"output/Type.Equality/index.js","original":{"line":7,"column":9}},{"generated":{"line":8,"column":27},"source":"output/Type.Equality/index.js","original":{"line":7,"column":25}},{"generated":{"line":9,"column":0},"source":"output/Type.Equality/index.js","original":{"line":8,"column":4}},{"name":"dict","generated":{"line":9,"column":11},"source":"output/Type.Equality/index.js","original":{"line":8,"column":11}},{"name":"to","generated":{"line":9,"column":16},"source":"output/Type.Equality/index.js","original":{"line":8,"column":16}},{"generated":{"line":9,"column":18},"source":"output/Type.Equality/index.js","original":{"line":8,"column":4}},{"generated":{"line":10,"column":0},"source":"output/Type.Equality/index.js","original":{"line":9,"column":1}},{"generated":{"line":10,"column":1},"source":"output/Type.Equality/index.js","original":{"line":7,"column":0}},{"generated":{"line":11,"column":0},"source":"output/Type.Equality/index.js","original":{"line":10,"column":0}},{"name":"refl","generated":{"line":11,"column":4},"source":"output/Type.Equality/index.js","original":{"line":10,"column":4}},{"generated":{"line":11,"column":11},"source":"output/Type.Equality/index.js","original":{"line":10,"column":11}},{"name":"TypeEquals","generated":{"line":11,"column":15},"source":"output/Type.Equality/index.js","original":{"line":10,"column":15}},{"generated":{"line":11,"column":25},"source":"output/Type.Equality/index.js","original":{"line":10,"column":11}},{"generated":{"line":11,"column":26},"source":"output/Type.Equality/index.js","original":{"line":10,"column":26}},{"name":"a","generated":{"line":11,"column":36},"source":"output/Type.Equality/index.js","original":{"line":10,"column":36}},{"generated":{"line":11,"column":37},"source":"output/Type.Equality/index.js","original":{"line":10,"column":26}},{"generated":{"line":11,"column":39},"source":"output/Type.Equality/index.js","original":{"line":10,"column":39}},{"generated":{"line":12,"column":0},"source":"output/Type.Equality/index.js","original":{"line":11,"column":4}},{"name":"a","generated":{"line":12,"column":11},"source":"output/Type.Equality/index.js","original":{"line":11,"column":11}},{"generated":{"line":12,"column":12},"source":"output/Type.Equality/index.js","original":{"line":11,"column":4}},{"generated":{"line":13,"column":0},"source":"output/Type.Equality/index.js","original":{"line":12,"column":1}},{"generated":{"line":13,"column":1},"source":"output/Type.Equality/index.js","original":{"line":10,"column":11}},{"generated":{"line":13,"column":3},"source":"output/Type.Equality/index.js","original":{"line":12,"column":3}},{"name":"a","generated":{"line":13,"column":13},"source":"output/Type.Equality/index.js","original":{"line":12,"column":13}},{"generated":{"line":13,"column":14},"source":"output/Type.Equality/index.js","original":{"line":12,"column":3}},{"generated":{"line":13,"column":16},"source":"output/Type.Equality/index.js","original":{"line":12,"column":16}},{"generated":{"line":14,"column":0},"source":"output/Type.Equality/index.js","original":{"line":13,"column":4}},{"name":"a","generated":{"line":14,"column":11},"source":"output/Type.Equality/index.js","original":{"line":13,"column":11}},{"generated":{"line":14,"column":12},"source":"output/Type.Equality/index.js","original":{"line":13,"column":4}},{"generated":{"line":15,"column":0},"source":"output/Type.Equality/index.js","original":{"line":14,"column":1}},{"generated":{"line":15,"column":1},"source":"output/Type.Equality/index.js","original":{"line":10,"column":11}},{"generated":{"line":15,"column":2},"source":"output/Type.Equality/index.js","original":{"line":10,"column":0}},{"generated":{"line":16,"column":0},"source":"output/Type.Equality/index.js","original":{"line":15,"column":0}},{"name":"from","generated":{"line":16,"column":4},"source":"output/Type.Equality/index.js","original":{"line":15,"column":4}},{"generated":{"line":16,"column":11},"source":"output/Type.Equality/index.js","original":{"line":15,"column":11}},{"name":"from","generated":{"line":16,"column":20},"source":"output/Type.Equality/index.js","original":{"line":15,"column":4}},{"generated":{"line":16,"column":24},"source":"output/Type.Equality/index.js","original":{"line":15,"column":11}},{"name":"dict","generated":{"line":16,"column":25},"source":"output/Type.Equality/index.js","original":{"line":15,"column":21}},{"generated":{"line":16,"column":29},"source":"output/Type.Equality/index.js","original":{"line":15,"column":11}},{"generated":{"line":16,"column":31},"source":"output/Type.Equality/index.js","original":{"line":15,"column":27}},{"generated":{"line":17,"column":0},"source":"output/Type.Equality/index.js","original":{"line":16,"column":4}},{"name":"dict","generated":{"line":17,"column":11},"source":"output/Type.Equality/index.js","original":{"line":16,"column":11}},{"name":"from","generated":{"line":17,"column":16},"source":"output/Type.Equality/index.js","original":{"line":16,"column":16}},{"generated":{"line":17,"column":20},"source":"output/Type.Equality/index.js","original":{"line":16,"column":4}},{"generated":{"line":18,"column":0},"source":"output/Type.Equality/index.js","original":{"line":17,"column":1}},{"generated":{"line":18,"column":1},"source":"output/Type.Equality/index.js","original":{"line":15,"column":0}},{"name":"module","generated":{"line":19,"column":0},"source":"output/Type.Equality/index.js","original":{"line":18,"column":0}},{"name":"exports","generated":{"line":19,"column":7},"source":"output/Type.Equality/index.js","original":{"line":18,"column":7}},{"generated":{"line":19,"column":14},"source":"output/Type.Equality/index.js","original":{"line":18,"column":0}},{"generated":{"line":19,"column":17},"source":"output/Type.Equality/index.js","original":{"line":18,"column":17}},{"name":"TypeEquals","generated":{"line":20,"column":0},"source":"output/Type.Equality/index.js","original":{"line":19,"column":4}},{"name":"TypeEquals","generated":{"line":20,"column":16},"source":"output/Type.Equality/index.js","original":{"line":19,"column":16}},{"generated":{"line":20,"column":26},"source":"output/Type.Equality/index.js","original":{"line":18,"column":17}},{"name":"to","generated":{"line":21,"column":0},"source":"output/Type.Equality/index.js","original":{"line":20,"column":4}},{"name":"to","generated":{"line":21,"column":8},"source":"output/Type.Equality/index.js","original":{"line":20,"column":8}},{"generated":{"line":21,"column":10},"source":"output/Type.Equality/index.js","original":{"line":18,"column":17}},{"name":"from","generated":{"line":22,"column":0},"source":"output/Type.Equality/index.js","original":{"line":21,"column":4}},{"name":"from","generated":{"line":22,"column":10},"source":"output/Type.Equality/index.js","original":{"line":21,"column":10}},{"generated":{"line":22,"column":14},"source":"output/Type.Equality/index.js","original":{"line":18,"column":17}},{"name":"refl","generated":{"line":23,"column":0},"source":"output/Type.Equality/index.js","original":{"line":22,"column":4}},{"name":"refl","generated":{"line":23,"column":10},"source":"output/Type.Equality/index.js","original":{"line":22,"column":10}},{"generated":{"line":24,"column":0},"source":"output/Type.Equality/index.js","original":{"line":18,"column":17}},{"generated":{"line":24,"column":1},"source":"output/Type.Equality/index.js","original":{"line":18,"column":0}}],"sources":{"output/Type.Equality/index.js":"// Generated by purs version 0.12.0\n\"use strict\";\nvar TypeEquals = function (from, to) {\n    this.from = from;\n    this.to = to;\n};\nvar to = function (dict) {\n    return dict.to;\n};\nvar refl = new TypeEquals(function (a) {\n    return a;\n}, function (a) {\n    return a;\n});\nvar from = function (dict) {\n    return dict.from;\n};\nmodule.exports = {\n    TypeEquals: TypeEquals,\n    to: to,\n    from: from,\n    refl: refl\n};\n"},"lineCount":null}},"hash":"7e3499dd6f3685b0d0a240a31fefdaca","cacheData":{"env":{}},"id":138}